injectme/__init__.py
injectme/errors.py
injectme/injector.py
injectme/registry.py
injectme/simple_api.py
injectme-0.0.6.dist-info/LICENSE
injectme-0.0.6.dist-info/METADATA
injectme-0.0.6.dist-info/WHEEL
injectme-0.0.6.dist-info/top_level.txt
injectme-0.0.6.dist-info/RECORD
