Metadata-Version: 2.1
Name: injectme
Version: 0.0.6
Summary: Small DI library
Home-page: https://github.com/zuczekgnojak/injectme
Author: zuczekgnojak
Project-URL: Documentation, https://injectme.readthedocs.io
Project-URL: Source, https://github.com/zuczekgnojak/injectme
Classifier: Development Status :: 3 - Alpha
Classifier: Programming Language :: Python :: 3
Classifier: License :: OSI Approved :: BSD License
Classifier: Operating System :: OS Independent
Requires-Python: >=3.7
License-File: LICENSE
